LICENSE.txt
MANIFEST.in
README.rst
readme.rst
requirements.txt
setup.cfg
setup.py
pyknackhq/__init__.py
pyknackhq/client.py
pyknackhq/datatype.py
pyknackhq/js.py
pyknackhq/py23compatible.py
pyknackhq/schema.py
pyknackhq/zzz_manual_install.py
pyknackhq.egg-info/PKG-INFO
pyknackhq.egg-info/SOURCES.txt
pyknackhq.egg-info/dependency_links.txt
pyknackhq.egg-info/requires.txt
pyknackhq.egg-info/top_level.txt
pyknackhq/tests/__init__.py
pyknackhq/tests/test_doc.py
pyknackhq/tests/test_example_get_response.py
pyknackhq/tests/test_upload.py